_piqtree2.cpython-312-darwin.so
piqtree2-0.3.1.dist-info/RECORD
piqtree2-0.3.1.dist-info/LICENSE
piqtree2-0.3.1.dist-info/WHEEL
piqtree2-0.3.1.dist-info/entry_points.txt
piqtree2-0.3.1.dist-info/top_level.txt
piqtree2-0.3.1.dist-info/METADATA
piqtree2/__init__.py
piqtree2/py.typed
piqtree2/exceptions.py
piqtree2/_libiqtree/_piqtree2.cpp
piqtree2/model/_options.py
piqtree2/model/_freq_type.py
piqtree2/model/__init__.py
piqtree2/model/_substitution_model.py
piqtree2/model/_rate_type.py
piqtree2/model/_model.py
piqtree2/iqtree/_decorator.py
piqtree2/iqtree/__init__.py
piqtree2/iqtree/_random_tree.py
piqtree2/iqtree/_robinson_foulds.py
piqtree2/iqtree/_tree.py
piqtree2/_app/__init__.py
