Metadata-Version: 2.1
Name: piqtree2
Version: 0.3.1
Summary: Python bindings for IQTree
Author: Gavin Huttley, Robert McArthur, Bui Quang Minh , Richard Morris, Thomas Wong
Project-URL: Repository, https://github.com/cogent3/piqtree2
Classifier: Development Status :: 2 - Pre-Alpha
Classifier: Intended Audience :: Science/Research
Classifier: Topic :: Scientific/Engineering :: Bio-Informatics
Classifier: Topic :: Software Development :: Libraries :: Python Modules
Classifier: License :: OSI Approved :: GNU General Public License v2 (GPLv2)
Classifier: Natural Language :: English
Classifier: Operating System :: MacOS
Classifier: Operating System :: POSIX :: Linux
Classifier: Programming Language :: C++
Classifier: Programming Language :: Python :: 3
Classifier: Programming Language :: Python :: 3.9
Classifier: Programming Language :: Python :: 3.10
Classifier: Programming Language :: Python :: 3.11
Classifier: Programming Language :: Python :: 3.12
Classifier: Typing :: Typed
Requires-Python: <3.13,>=3.9
License-File: LICENSE
Requires-Dist: cogent3
Requires-Dist: pyyaml
Provides-Extra: dev
Requires-Dist: cibuildwheel ; extra == 'dev'
Requires-Dist: pybind11 ; extra == 'dev'
Requires-Dist: ruff ; extra == 'dev'
Requires-Dist: scriv ; extra == 'dev'
Requires-Dist: piqtree2[test] ; extra == 'dev'
Provides-Extra: test
Requires-Dist: pytest ; extra == 'test'
Requires-Dist: pytest-cov ; extra == 'test'
Requires-Dist: nox ; extra == 'test'
